LICENSE
MANIFEST.in
requirements.txt
setup.py
hcs.egg-info/PKG-INFO
hcs.egg-info/SOURCES.txt
hcs.egg-info/dependency_links.txt
hcs.egg-info/entry_points.txt
hcs.egg-info/top_level.txt
hiddenconsolestart/__main__.py
hiddenconsolestart/hcs.py
hiddenconsolestart/main.py
hiddenconsolestart/metadata.py
hiddenconsolestart/process.py