Metadata-Version: 1.1
Name: hcs
Version: 0.1.16
Summary: Hide console and execute applications in background
Home-page: https://github.com/RDCH106/hidden_console_start
Author: Rubén de Celis Hernández
Author-email: contact@rdch106.hol.es
License: MIT
Download-URL: https://github.com/RDCH106/hidden_console_start/archive/v0.1.16.tar.gz
Keywords: background console windows gnu-linux
Platform: UNKNOWN
Classifier: Programming Language :: Python
Classifier: Programming Language :: Python :: 2.7
Classifier: Programming Language :: Python :: 3.2
Classifier: Programming Language :: Python :: 3.3
Classifier: Programming Language :: Python :: 3.4
Classifier: Programming Language :: Python :: 3.5
Classifier: Programming Language :: Python :: 3.6
